{
  "board": [
    {
      "_id": "u102",
      "name": "Sprint 2",
      "creator": {
        "_id": "304",
        "fullName": "Nuki Ben David",
        "imgUrl": "https://www.img.com/101.png"
      },
      "statuses": [
        {
          "id": "801",
          "color": "#a8a8a8",
          "txt": ""
        },
        {
          "id": "803",
          "color": "#fdab3d",
          "txt": "Working on it"
        },
        {
          "id": "804",
          "color": "#e44258",
          "txt": "Stuck"
        },
        {
          "id": "805",
          "color": "#00ca72",
          "txt": "Done"
        }
      ],
      "priorities": [
        {
          "id": "704",
          "color": "#a8a8a8",
          "txt": ""
        },
        {
          "id": "701",
          "color": " #90d5ffd9",
          "txt": "Low"
        },
        {
          "id": "702",
          "color": "#c137c1ba",
          "txt": "Medium"
        },
        {
          "id": "703",
          "color": "#e44258",
          "txt": "High"
        }
      ],
      "activities": [],
      "members": [
        {
          "_id": "301",
          "fullName": "Puki Ben David",
          "imgUrl": "https://www.img.com/101.png",
          "password": "pass",
          "email": "muki@bendavid.com",
          "isAdmin": false
        },
        {
          "_id": "302",
          "fullName": "Muki Ben David",
          "imgUrl": "https://www.img.com/101.png",
          "password": "pass",
          "email": "muki@bendavid.com",
          "isAdmin": false
        }
      ],
      "groups": [
        {
          "id": "401",
          "color": "#aecbfa",
          "name": "task",
          "tasks": [
            {
              "id": "842",
              "txt": "hello",
              "members": [
                {
                  "_id": "302",
                  "fullName": "Muki Ben David",
                  "imgUrl": "https://www.img.com/101.png",
                  "password": "pass",
                  "email": "muki@bendavid.com",
                  "isAdmin": false
                },
                {
                  "_id": "301",
                  "fullName": "Puki Ben David",
                  "imgUrl": "https://www.img.com/101.png",
                  "password": "pass",
                  "email": "muki@bendavid.com",
                  "isAdmin": false
                },
                {
                  "_id": "303",
                  "fullName": "Loki Ben David",
                  "imgUrl": "https://www.img.com/101.png",
                  "password": "pass",
                  "email": "muki@bendavid.com",
                  "isAdmin": false
                }
              ],
              "dueDate": "",
              "status": {
                "id": "803",
                "color": "#fdab3d",
                "txt": "Working on it"
              },
              "priority": {
                "id": "701",
                "color": " #90d5ffd9",
                "txt": "Low"
              },
              "posts": []
            },
            {
              "txt": "yuval",
              "members": [
                {
                  "_id": "302",
                  "fullName": "Muki Ben David",
                  "imgUrl": "https://www.img.com/101.png",
                  "password": "pass",
                  "email": "muki@bendavid.com",
                  "isAdmin": false
                },
                {
                  "_id": "301",
                  "fullName": "Puki Ben David",
                  "imgUrl": "https://www.img.com/101.png",
                  "password": "pass",
                  "email": "muki@bendavid.com",
                  "isAdmin": false
                }
              ],
              "dueDate": "",
              "status": {
                "id": "804",
                "color": "#e44258",
                "txt": "Stuck"
              },
              "priority": {
                "id": "702",
                "color": "#c137c1ba",
                "txt": "Medium"
              },
              "posts": [],
              "id": "dKRdP"
            },
            {
              "txt": "hhhhhhhhh",
              "members": [
                {
                  "_id": "302",
                  "fullName": "Muki Ben David",
                  "imgUrl": "https://www.img.com/101.png",
                  "password": "pass",
                  "email": "muki@bendavid.com",
                  "isAdmin": false
                },
                {
                  "_id": "301",
                  "fullName": "Puki Ben David",
                  "imgUrl": "https://www.img.com/101.png",
                  "password": "pass",
                  "email": "muki@bendavid.com",
                  "isAdmin": false
                }
              ],
              "dueDate": "",
              "status": {
                "id": "805",
                "color": "#00ca72",
                "txt": "Done"
              },
              "priority": {
                "id": "703",
                "color": "#e44258",
                "txt": "High"
              },
              "posts": [],
              "id": "nnqUL"
            }
          ]
        },
        {
          "id": "402",
          "color": "#fff475",
          "name": "5565623 ",
          "tasks": [
            {
              "id": "920",
              "txt": "txt",
              "members": [
                {
                  "_id": "301",
                  "fullName": "Puki Ben David",
                  "imgUrl": "https://www.img.com/101.png",
                  "password": "pass",
                  "email": "muki@bendavid.com",
                  "isAdmin": false
                }
              ],
              "dueDate": "",
              "status": {
                "id": "805",
                "color": "#00ca72",
                "txt": "Done"
              },
              "priority": {
                "id": "702",
                "color": "#c137c1ba",
                "txt": "Medium"
              },
              "posts": []
            }
          ]
        }
      ]
    },
    {
      "name": "myBoard",
      "creator": {
        "_id": "304",
        "fullName": "Nuki Ben David",
        "imgUrl": "https://www.img.com/101.png"
      },
      "statuses": [
        {
          "id": "801",
          "color": "#a8a8a8",
          "txt": ""
        },
        {
          "id": "803",
          "color": "#fdab3d",
          "txt": "Working on it"
        },
        {
          "id": "804",
          "color": "#e44258",
          "txt": "Stuck"
        },
        {
          "id": "805",
          "color": "#00ca72",
          "txt": "Done"
        }
      ],
      "priorities": [
        {
          "id": "704",
          "color": "#a8a8a8",
          "txt": ""
        },
        {
          "id": "701",
          "color": " #90d5ffd9",
          "txt": "Low"
        },
        {
          "id": "702",
          "color": "#c137c1ba",
          "txt": "Medium"
        },
        {
          "id": "703",
          "color": "#e44258",
          "txt": "High"
        }
      ],
      "activities": [],
      "members": [],
      "groups": [
        {
          "id": "401",
          "color": "pink",
          "name": "Backend",
          "tasks": [
            {
              "id": "840",
              "txt": "heeeeeee",
              "members": [],
              "dueDate": null,
              "status": {
                "id": "803",
                "color": "#fdab3d",
                "txt": "Working on it"
              },
              "priority": {
                "id": "701",
                "color": " #90d5ffd9",
                "txt": "Low"
              },
              "posts": []
            },
            {
              "id": "842",
              "txt": "txdddddt",
              "members": [],
              "dueDate": null,
              "status": {
                "id": "803",
                "color": "#fdab3d",
                "txt": "Working on it"
              },
              "priority": {
                "id": "701",
                "color": " #90d5ffd9",
                "txt": "Low"
              },
              "posts": []
            }
          ]
        },
        {
          "id": "402",
          "color": "black",
          "name": "Frontend",
          "tasks": [
            {
              "id": "920",
              "txt": "txt",
              "members": [],
              "dueDate": "",
              "status": {
                "id": "805",
                "color": "#00ca72",
                "txt": "Done"
              },
              "priority": {
                "id": "702",
                "color": "#c137c1ba",
                "txt": "Medium"
              },
              "posts": []
            },
            {
              "txt": "dddddddddddd",
              "members": [],
              "dueDate": "",
              "status": {
                "color": "#a8a8a8",
                "txt": "",
                "id": "pUaZT"
              },
              "priority": {
                "color": "#a8a8a8",
                "txt": "",
                "id": "O0bE1"
              },
              "posts": [],
              "id": "r6uF8"
            },
            {
              "txt": "",
              "members": [],
              "dueDate": "",
              "status": {
                "color": "#a8a8a8",
                "txt": "",
                "id": "s7jDu"
              },
              "priority": {
                "color": "#a8a8a8",
                "txt": "",
                "id": "fGkYE"
              },
              "posts": [],
              "id": "rRRob"
            },
            {
              "txt": "dddddd",
              "members": [],
              "dueDate": "",
              "status": {
                "color": "#a8a8a8",
                "txt": "",
                "id": "jpXni"
              },
              "priority": {
                "color": "#a8a8a8",
                "txt": "",
                "id": "EJKUM"
              },
              "posts": [],
              "id": "DYhW7"
            },
            {
              "txt": "dddddddddddddd",
              "members": [],
              "dueDate": "",
              "status": {
                "color": "#a8a8a8",
                "txt": "",
                "id": "yQhZC"
              },
              "priority": {
                "color": "#a8a8a8",
                "txt": "",
                "id": "vbPCt"
              },
              "posts": [],
              "id": "2kA46"
            }
          ]
        },
        {
          "color": "black",
          "name": "New Group",
          "tasks": [
            {
              "txt": "txt",
              "members": [],
              "dueDate": "",
              "status": {
                "color": "#a8a8a8",
                "txt": "",
                "id": "4VF2K"
              },
              "priority": {
                "color": "#a8a8a8",
                "txt": "",
                "id": "ZxUoe"
              },
              "posts": [],
              "id": "N54ht"
            },
            {
              "txt": "txt",
              "members": [],
              "dueDate": "",
              "status": {
                "color": "#a8a8a8",
                "txt": "",
                "id": "xCBeI"
              },
              "priority": {
                "color": "#a8a8a8",
                "txt": "",
                "id": "NEGBb"
              },
              "posts": [],
              "id": "pSHmO"
            }
          ],
          "id": "qwwNh"
        },
        {
          "color": "black",
          "name": "New Group",
          "tasks": [
            {
              "txt": "txt",
              "members": [],
              "dueDate": "",
              "status": {
                "color": "gray",
                "txt": "",
                "id": "6616H"
              },
              "priority": {
                "color": "gray",
                "txt": "",
                "id": "i2rjN"
              },
              "posts": [],
              "id": "Djw6P"
            },
            {
              "txt": "txt",
              "members": [],
              "dueDate": "",
              "status": {
                "color": "gray",
                "txt": "",
                "id": "kvtF5"
              },
              "priority": {
                "color": "gray",
                "txt": "",
                "id": "0TUMD"
              },
              "posts": [],
              "id": "4E41w"
            }
          ],
          "id": "9yaH9"
        }
      ],
      "_id": "ssNl8Rw"
    },
    {
      "name": "myBoard",
      "creator": {
        "_id": "304",
        "fullName": "Nuki Ben David",
        "imgUrl": "https://www.img.com/101.png"
      },
      "statuses": [
        {
          "id": "801",
          "color": "#a8a8a8",
          "txt": ""
        },
        {
          "id": "803",
          "color": "#fdab3d",
          "txt": "Working on it"
        },
        {
          "id": "804",
          "color": "#e44258",
          "txt": "Stuck"
        },
        {
          "id": "805",
          "color": "#00ca72",
          "txt": "Done"
        }
      ],
      "priorities": [
        {
          "id": "704",
          "color": "#a8a8a8",
          "txt": ""
        },
        {
          "id": "701",
          "color": " #90d5ffd9",
          "txt": "Low"
        },
        {
          "id": "702",
          "color": "#c137c1ba",
          "txt": "Medium"
        },
        {
          "id": "703",
          "color": "#e44258",
          "txt": "High"
        }
      ],
      "activities": [],
      "members": [],
      "groups": [
        {
          "id": "401",
          "color": "#aecbfa",
          "name": "Backend",
          "tasks": [
            {
              "id": "840",
              "txt": "txt",
              "members": [],
              "dueDate": "",
              "status": {
                "id": "801",
                "color": "#a8a8a8",
                "txt": ""
              },
              "priority": {
                "id": "704",
                "color": "#a8a8a8",
                "txt": ""
              },
              "posts": []
            },
            {
              "id": "842",
              "txt": "txt",
              "members": [],
              "dueDate": "",
              "status": {
                "id": "801",
                "color": "#a8a8a8",
                "txt": ""
              },
              "priority": {
                "id": "704",
                "color": "#a8a8a8",
                "txt": ""
              },
              "posts": []
            }
          ]
        },
        {
          "color": "#cbf0f8",
          "name": "Frontend",
          "tasks": [
            {
              "txt": "txt",
              "members": [],
              "dueDate": "",
              "status": {
                "color": "gray",
                "txt": "",
                "id": "wk9Ic"
              },
              "priority": {
                "color": "gray",
                "txt": "",
                "id": "yodta"
              },
              "posts": [],
              "id": "cw3kM"
            }
          ],
          "id": "sGhKT"
        }
      ],
      "_id": "kr5Yxf5"
    },
    {
      "name": "MysdBoard",
      "creator": {
        "_id": "304",
        "fullName": "Nuki Ben David",
        "imgUrl": "https://www.img.com/101.png"
      },
      "statuses": [
        {
          "id": "801",
          "color": "#a8a8a8",
          "txt": ""
        },
        {
          "id": "803",
          "color": "#fdab3d",
          "txt": "Working on it"
        },
        {
          "id": "804",
          "color": "#e44258",
          "txt": "Stuck"
        },
        {
          "id": "805",
          "color": "#00ca72",
          "txt": "Done"
        }
      ],
      "priorities": [
        {
          "id": "704",
          "color": "#a8a8a8",
          "txt": ""
        },
        {
          "id": "701",
          "color": " #90d5ffd9",
          "txt": "Low"
        },
        {
          "id": "702",
          "color": "#c137c1ba",
          "txt": "Medium"
        },
        {
          "id": "703",
          "color": "#e44258",
          "txt": "High"
        }
      ],
      "activities": [],
      "members": [],
      "groups": [
        {
          "id": "401",
          "color": "black",
          "name": "Backend",
          "tasks": [
            {
              "id": "840",
              "txt": "txt",
              "members": [],
              "dueDate": "",
              "status": {
                "id": "801",
                "color": "#a8a8a8",
                "txt": ""
              },
              "priority": {
                "id": "704",
                "color": "#a8a8a8",
                "txt": ""
              },
              "posts": []
            },
            {
              "id": "842",
              "txt": "txt",
              "members": [],
              "dueDate": "",
              "status": {
                "id": "801",
                "color": "#a8a8a8",
                "txt": ""
              },
              "priority": {
                "id": "704",
                "color": "#a8a8a8",
                "txt": ""
              },
              "posts": []
            }
          ]
        },
        {
          "id": "402",
          "color": "black",
          "name": "Frontend",
          "tasks": [
            {
              "id": "920",
              "txt": "txt",
              "members": [],
              "dueDate": "",
              "status": {
                "id": "801",
                "color": "#a8a8a8",
                "txt": ""
              },
              "priority": {
                "id": "704",
                "color": "#a8a8a8",
                "txt": ""
              },
              "posts": []
            }
          ]
        }
      ],
      "_id": "NmouDt_"
    },
    {
      "name": "myBoard",
      "creator": {
        "_id": "304",
        "fullName": "Muki Ben David",
        "imgUrl": "https://www.img.com/101.png"
      },
      "statuses": [
        {
          "color": "gray",
          "txt": "",
          "id": "7HYup"
        },
        {
          "color": "yellow",
          "txt": "Working on it",
          "id": "lNmuR"
        },
        {
          "color": "red",
          "txt": "Stuck",
          "id": "wd0m3"
        },
        {
          "color": "green",
          "txt": "Done",
          "id": "fSevU"
        }
      ],
      "priorities": [
        {
          "color": "gray",
          "txt": "",
          "id": "piHW3"
        },
        {
          "color": "lightblue",
          "txt": "Low",
          "id": "DRvvn"
        },
        {
          "color": "purple",
          "txt": "Medium",
          "id": "iJZUB"
        },
        {
          "color": "red",
          "txt": "High",
          "id": "kyB0l"
        }
      ],
      "activities": [],
      "members": [],
      "groups": [
        {
          "color": "#ffffff",
          "name": "BackEnd",
          "tasks": [
            {
              "txt": "txt",
              "members": [],
              "dueDate": "",
              "status": {
                "color": "gray",
                "txt": "",
                "id": "h8vlH"
              },
              "priority": {
                "color": "gray",
                "txt": "",
                "id": "l8m8x"
              },
              "posts": [],
              "id": "mY12g"
            },
            {
              "txt": "txt",
              "members": [],
              "dueDate": "",
              "status": {
                "color": "gray",
                "txt": "",
                "id": "VM2Xf"
              },
              "priority": {
                "color": "gray",
                "txt": "",
                "id": "RErnc"
              },
              "posts": [],
              "id": "86aRx"
            }
          ],
          "id": "Vzzfl"
        },
        {
          "color": "#ffffff",
          "name": "Frontend",
          "tasks": [
            {
              "txt": "txt",
              "members": [],
              "dueDate": "",
              "status": {
                "color": "gray",
                "txt": "",
                "id": "wk9Ic"
              },
              "priority": {
                "color": "gray",
                "txt": "",
                "id": "yodta"
              },
              "posts": [],
              "id": "cw3kM"
            }
          ],
          "id": "sGhKT"
        }
      ],
      "_id": "x_R-pBM"
    },
    {
      "name": "myBoard",
      "creator": {
        "_id": "301",
        "fullName": "Puki Ben David",
        "imgUrl": "https://www.img.com/101.png",
        "password": "pass",
        "email": "muki@bendavid.com",
        "isAdmin": false
      },
      "statuses": [
        {
          "color": "gray",
          "txt": "",
          "id": "q6TvE"
        },
        {
          "color": "yellow",
          "txt": "Working on it",
          "id": "hWXbO"
        },
        {
          "color": "red",
          "txt": "Stuck",
          "id": "2sV1w"
        },
        {
          "color": "green",
          "txt": "Done",
          "id": "20WLN"
        }
      ],
      "priorities": [
        {
          "color": "gray",
          "txt": "",
          "id": "t7kLH"
        },
        {
          "color": "lightblue",
          "txt": "Low",
          "id": "dGIRZ"
        },
        {
          "color": "purple",
          "txt": "Medium",
          "id": "1mTLr"
        },
        {
          "color": "red",
          "txt": "High",
          "id": "V4uiD"
        }
      ],
      "activities": [],
      "members": [],
      "groups": [
        {
          "color": "#ffffff",
          "name": "BackEnd",
          "tasks": [
            {
              "txt": "txt",
              "members": [],
              "dueDate": "",
              "status": {
                "color": "gray",
                "txt": "",
                "id": "0Fy8v"
              },
              "priority": {
                "color": "gray",
                "txt": "",
                "id": "KEU72"
              },
              "posts": [],
              "id": "twfOK"
            },
            {
              "txt": "txt",
              "members": [],
              "dueDate": "",
              "status": {
                "color": "gray",
                "txt": "",
                "id": "s7MvG"
              },
              "priority": {
                "color": "gray",
                "txt": "",
                "id": "S15gM"
              },
              "posts": [],
              "id": "OQhMS"
            }
          ],
          "id": "0Pc33"
        },
        {
          "color": "#ffffff",
          "name": "Frontend",
          "tasks": [
            {
              "txt": "txt",
              "members": [],
              "dueDate": "",
              "status": {
                "color": "gray",
                "txt": "",
                "id": "BB8fu"
              },
              "priority": {
                "color": "gray",
                "txt": "",
                "id": "Ebqvn"
              },
              "posts": [],
              "id": "By8vl"
            }
          ],
          "id": "zn9yR"
        }
      ],
      "_id": "GGJx2pi"
    },
    {
      "name": "Guy Board  ",
      "creator": {
        "_id": "301",
        "fullName": "Puki Ben David",
        "imgUrl": "https://www.img.com/101.png",
        "password": "pass",
        "email": "muki@bendavid.com",
        "isAdmin": false
      },
      "statuses": [
        {
          "color": "gray",
          "txt": "",
          "id": "KYibi"
        },
        {
          "color": "yellow",
          "txt": "Working on it",
          "id": "JOpip"
        },
        {
          "color": "red",
          "txt": "Stuck",
          "id": "Jkd8w"
        },
        {
          "color": "green",
          "txt": "Done",
          "id": "o15s2"
        }
      ],
      "priorities": [
        {
          "color": "gray",
          "txt": "",
          "id": "sNEtR"
        },
        {
          "color": "lightblue",
          "txt": "Low",
          "id": "ut7WL"
        },
        {
          "color": "purple",
          "txt": "Medium",
          "id": "Vlk36"
        },
        {
          "color": "red",
          "txt": "High",
          "id": "vgziR"
        }
      ],
      "activities": [],
      "members": [],
      "groups": [
        {
          "color": "#ffffff",
          "name": "BackEnd",
          "tasks": [
            {
              "txt": "txt",
              "members": [],
              "dueDate": "",
              "status": {
                "color": "gray",
                "txt": "",
                "id": "GlzSN"
              },
              "priority": {
                "color": "gray",
                "txt": "",
                "id": "FERYQ"
              },
              "posts": [],
              "id": "9IoSr"
            },
            {
              "txt": "txt",
              "members": [],
              "dueDate": "",
              "status": {
                "color": "gray",
                "txt": "",
                "id": "nrLuW"
              },
              "priority": {
                "color": "gray",
                "txt": "",
                "id": "C0wqX"
              },
              "posts": [],
              "id": "NXWRa"
            }
          ],
          "id": "VrdgM"
        },
        {
          "color": "#ffffff",
          "name": "Frontend",
          "tasks": [
            {
              "txt": "txt",
              "members": [],
              "dueDate": "",
              "status": {
                "color": "gray",
                "txt": "",
                "id": "igaLj"
              },
              "priority": {
                "color": "gray",
                "txt": "",
                "id": "qQkbX"
              },
              "posts": [],
              "id": "FXcTa"
            }
          ],
          "id": "ZMZ8P"
        }
      ],
      "_id": "8hf5Ths"
    }
  ],
  "user": [
    {
      "_id": "301",
      "fullName": "Puki Ben David",
      "imgUrl": "https://www.img.com/101.png",
      "password": "pass",
      "email": "muki@bendavid.com",
      "isAdmin": false
    },
    {
      "_id": "302",
      "fullName": "Muki Ben David",
      "imgUrl": "https://www.img.com/101.png",
      "password": "pass",
      "email": "muki@bendavid.com",
      "isAdmin": false
    },
    {
      "_id": "303",
      "fullName": "Loki Ben David",
      "imgUrl": "https://www.img.com/101.png",
      "password": "pass",
      "email": "muki@bendavid.com",
      "isAdmin": false
    },
    {
      "_id": "304",
      "fullName": "Nuki Ben David",
      "imgUrl": "https://www.img.com/101.png",
      "password": "pass",
      "email": "muki@bendavid.com",
      "isAdmin": false
    }
  ]
}